sensing_network/convert_utils.py
sensing_network/layout_adjustment.py
sensing_network/network_layout.py
sensing_network/pipeline.py
sensing_network/resistance_optimization.py
sensing_network/resistor_link_selection.py
sensing_network/resistor_path_generation.py
sensing_network-0.7.dist-info/LICENSE.txt
sensing_network-0.7.dist-info/METADATA
sensing_network-0.7.dist-info/WHEEL
sensing_network-0.7.dist-info/top_level.txt
sensing_network-0.7.dist-info/RECORD
